LICENSE
MANIFEST.in
README.md
setup.py
deploy/__init__.py
deploy/apps.py
deploy/management/__init__.py
deploy/management/commands/__init__.py
deploy/management/commands/deploy.py
deploy/management/commands/nginx_conf.py
deploy/management/commands/pm2_conf.py
deploy/templates/__init__.py
deploy/templates/deploy/__init__.py
deploy/templates/deploy/ecosystem.config.template
deploy/templates/deploy/nginx.conf.template
django_deploy_kit.egg-info/PKG-INFO
django_deploy_kit.egg-info/SOURCES.txt
django_deploy_kit.egg-info/dependency_links.txt
django_deploy_kit.egg-info/top_level.txt